moorcheh_sdk/__init__.py
moorcheh_sdk/_base_client.py
moorcheh_sdk/_client.py
moorcheh_sdk/_legacy_client.py
moorcheh_sdk/_version.py
moorcheh_sdk/exceptions.py
moorcheh_sdk/py.typed
moorcheh_sdk/resources/__init__.py
moorcheh_sdk/resources/answer.py
moorcheh_sdk/resources/base.py
moorcheh_sdk/resources/documents.py
moorcheh_sdk/resources/namespaces.py
moorcheh_sdk/resources/search.py
moorcheh_sdk/resources/vectors.py
moorcheh_sdk/types/__init__.py
moorcheh_sdk/types/answer.py
moorcheh_sdk/types/common.py
moorcheh_sdk/types/document.py
moorcheh_sdk/types/namespace.py
moorcheh_sdk/types/search.py
moorcheh_sdk/types/vector.py
moorcheh_sdk/utils/batching.py
moorcheh_sdk/utils/constants.py
moorcheh_sdk/utils/decorators.py
moorcheh_sdk/utils/logging.py
moorcheh_sdk-1.3.1.dist-info/METADATA
moorcheh_sdk-1.3.1.dist-info/WHEEL
moorcheh_sdk-1.3.1.dist-info/licenses/LICENSE
moorcheh_sdk-1.3.1.dist-info/RECORD
