Metadata-Version: 2.4
Name: moorcheh-sdk
Version: 1.3.1
Summary: Python SDK for the Moorcheh Semantic Search API
Project-URL: Homepage, https://www.moorcheh.ai
Project-URL: Repository, https://github.com/moorcheh-ai/moorcheh-python-sdk
Author: Majid Fekri majid.fekri@edgeaiinnovations.com
License-Expression: MIT
License-File: LICENSE
Keywords: ai,moorcheh,sdk,semantic search,vector search
Requires-Python: <4,>=3.10
Requires-Dist: httpx<0.29,>=0.28.1
